kortt/__init__.py
kortt/generator.py
koRTT-0.0.3.dist-info/METADATA
koRTT-0.0.3.dist-info/WHEEL
koRTT-0.0.3.dist-info/top_level.txt
koRTT-0.0.3.dist-info/RECORD
