Metadata-Version: 2.1
Name: koRTT
Version: 0.0.3
Summary: Round Trip Translation tool for Korean data augmentation
Home-page: https://github.com/FacerAin/koRTT
Author: FacerAin
Author-email: ywsong.dev@kakao.com
License: MIT
Requires-Python: >=3
Requires-Dist: googletrans (==4.0.0rc1)
